{"id":"PYcsBwJNrZUfwdouFyrpG","type":"page","documentClass":"CategoryPage","contents":{"en-US":{"title":"Category Page","slug":"category-page","includeInSiteMap":true,"statusMap":{},"isCustomSlug":false,"tags":{},"dataFields":[{"name":"metaDescription","value":"This is an article page","type":"string"},{"name":"metaRobots","value":"index,follow","type":"string"}],"documentAreas":[{"name":"pageBody","blocks":[{"id":"6nk53XqEpzI_mMGl2jxN5","name":"defaultHeroBlock","components":[{"name":"heroTitle","instances":[{"id":"2pY816d7wWCECrfTeykg8","props":[{"name":"text","type":"HeaderText","fieldContent":{"htmlText":"<h1>A category page</h1>"}}]}]},{"name":"heroDescription","instances":[{"id":"Kke4J-pYXhCDzn2gbDVK_","props":[{"name":"text","type":"ParagraphText","fieldContent":{"htmlText":"<p>A category page organizes articles by topic or theme, making it easy for users to find and explore related content.</p>"}}]}]},{"name":"heroImage","instances":[{"id":"94ybc-VWx684SkM9zj3io","props":[{"name":"image","type":"Image","fieldContent":{"src":"/_assets/images/category-1.svg","alt":"Category Page Hero Image","focusX":39.43,"focusY":29.91}}]}]}]},{"id":"5BJX59xwxNiIjXTA8urEE","name":"articlesGalleryBlock","components":[{"name":"galleryHeading","instances":[{"id":"OeopUxRZtLFXPY-aZK-cY","props":[{"name":"text","type":"HeaderText","fieldContent":{"htmlText":"<h2>Articles in this category</h2>"}}]}]},{"name":"galleryListing","instances":[{"id":"7G1VAYJ_pJaqVcSBD04Zx","props":[{"name":"documentsList","type":"DocumentsList","fieldContent":{"isRequired":false,"selectionMode":"selectDocuments","allowedDocumentClasses":["ArticlePage"],"selectDocumentAreas":["card"],"documentsIds":["UVB25FSXrZpMEiB5ef7B9"]}}]}]}]}]},{"name":"card","blocks":[{"id":"mkF9A4i6vf9sumjx8yBMZ","name":"cardImageBlock","components":[{"name":"cardViewImage","instances":[{"id":"_qOtfVhKoI-5I_2_TgW68","props":[{"name":"image","type":"Image","fieldContent":{"src":"/_assets/images/category-1.svg","alt":"Category Page Card Image"}}]}]}]},{"id":"V6fIQjMwxJWD_wr2PkGBE","name":"cardTitleBlock","components":[{"name":"cardTitle","instances":[{"id":"p_jyWxS9mjykmt6fnRMod","props":[{"name":"text","type":"ParagraphText","fieldContent":{"htmlText":"<h5>Category Page</h5>"}}]}]}]}]}],"dateUpdated":1683801730671,"authors":{"apustovalov@gmail.com":1683801730671}}}}